nonebot_plugin_rollpig/__init__.py
nonebot_plugin_rollpig/resource/image/android-pig.png
nonebot_plugin_rollpig/resource/image/apple-pig.png
nonebot_plugin_rollpig/resource/image/bacon.png
nonebot_plugin_rollpig/resource/image/big-lazy-pig.png
nonebot_plugin_rollpig/resource/image/black-pig.png
nonebot_plugin_rollpig/resource/image/black-white-pig.png
nonebot_plugin_rollpig/resource/image/chained_crown_pig.png
nonebot_plugin_rollpig/resource/image/crystal-pig.png
nonebot_plugin_rollpig/resource/image/demon-pig.png
nonebot_plugin_rollpig/resource/image/doll-pig.png
nonebot_plugin_rollpig/resource/image/explosive-pig.png
nonebot_plugin_rollpig/resource/image/goblin-pig.png
nonebot_plugin_rollpig/resource/image/heaven-pig.png
nonebot_plugin_rollpig/resource/image/human.png
nonebot_plugin_rollpig/resource/image/invisible_pig.png
nonebot_plugin_rollpig/resource/image/landmine-pig.png
nonebot_plugin_rollpig/resource/image/lao_zhu_li.png
nonebot_plugin_rollpig/resource/image/magic-pig.png
nonebot_plugin_rollpig/resource/image/mc_porkchop.png
nonebot_plugin_rollpig/resource/image/mechanical-pig.png
nonebot_plugin_rollpig/resource/image/pig-ball.png
nonebot_plugin_rollpig/resource/image/pig-bun.png
nonebot_plugin_rollpig/resource/image/pig-cat.png
nonebot_plugin_rollpig/resource/image/pig-die.png
nonebot_plugin_rollpig/resource/image/pig-human.png
nonebot_plugin_rollpig/resource/image/pig-souffle.png
nonebot_plugin_rollpig/resource/image/pig-stamp.png
nonebot_plugin_rollpig/resource/image/pig-turtle.png
nonebot_plugin_rollpig/resource/image/pig.png
nonebot_plugin_rollpig/resource/image/pig_god.png
nonebot_plugin_rollpig/resource/image/pork-skewer.png
nonebot_plugin_rollpig/resource/image/rainbow-pig.png
nonebot_plugin_rollpig/resource/image/roasted-pig.png
nonebot_plugin_rollpig/resource/image/skeleton-pig.png
nonebot_plugin_rollpig/resource/image/snow-pig.png
nonebot_plugin_rollpig/resource/image/soul-pig.png
nonebot_plugin_rollpig/resource/image/tangyuan_pig.png
nonebot_plugin_rollpig-0.2.5.dist-info/licenses/LICENSE
nonebot_plugin_rollpig-0.2.5.dist-info/METADATA
nonebot_plugin_rollpig-0.2.5.dist-info/WHEEL
nonebot_plugin_rollpig-0.2.5.dist-info/RECORD
