Metadata-Version: 2.4
Name: nonebot_plugin_rollpig
Version: 0.2.5
Summary: 今天是什么小猪
License: MIT
License-File: LICENSE
Author: Bear_lele
Author-email: lele2587342146@gmail.com
Requires-Python: >=3.9,<4.0
Classifier: License :: OSI Approved :: MIT License
Classifier: Programming Language :: Python :: 3
Classifier: Programming Language :: Python :: 3.9
Classifier: Programming Language :: Python :: 3.10
Classifier: Programming Language :: Python :: 3.11
Classifier: Programming Language :: Python :: 3.12
Classifier: Programming Language :: Python :: 3.13
Classifier: Programming Language :: Python :: 3.14
Requires-Dist: nonebot-adapter-onebot (>=2.4.0)
Requires-Dist: nonebot-plugin-apscheduler (>=0.5.0)
Requires-Dist: nonebot-plugin-htmlrender (>=0.6.7)
Requires-Dist: nonebot-plugin-localstore (>=0.7.4)
Requires-Dist: nonebot2 (>=2.4.0)
Project-URL: Homepage, https://github.com/Bearlele/nonebot-plugin-rollpig
